cloudutils/__init__.py
cloudutils/instance/__init__.py
cloudutils/instance/ec2.py
cloudutils/instance/gce.py
cloudutils/instance/instance.py
cloudutils/vault/__init__.py
cloudutils/vault/ec2.py
cloudutils/vault/gce.py
cloudutils/vault/vault.py
viant_cloudutils-0.1.7.dist-info/METADATA
viant_cloudutils-0.1.7.dist-info/WHEEL
viant_cloudutils-0.1.7.dist-info/top_level.txt
viant_cloudutils-0.1.7.dist-info/RECORD
