Metadata-Version: 2.1
Name: viant-cloudutils
Version: 0.1.7
Summary: Cloud utilities for automation
Home-page: https://github.vianttech.com/techops/cloudutils
Author: Lee Sautia
Author-email: lsautia@viantinc.com
License: UNKNOWN
Platform: UNKNOWN
Classifier: Programming Language :: Python :: 3
Classifier: License :: OSI Approved :: MIT License
Classifier: Operating System :: OS Independent
